Metadata-Version: 1.1
Name: yadi-py
Version: 0.0.9
Summary: Yadi wrapper that makes it seamlessly available as a local dependency
Home-page: https://github.yandex-team.ru/product-security/yadi
Author: Yandex IS Team
Author-email: buglloc@yandex-team.ru
License: UNKNOWN
Platform: UNKNOWN
Classifier: Development Status :: 3 - Alpha
Classifier: Environment :: Console
Classifier: Intended Audience :: Developers
Classifier: Topic :: Security
Classifier: Topic :: Software Development :: Quality Assurance
Classifier: Topic :: Software Development :: Testing
